tqsdk_zq_otg/__init__.py
tqsdk_zq_otg_rohon-1.1.2.dist-info/METADATA
tqsdk_zq_otg_rohon-1.1.2.dist-info/WHEEL
tqsdk_zq_otg_rohon-1.1.2.dist-info/top_level.txt
tqsdk_zq_otg_rohon-1.1.2.dist-info/RECORD
