Metadata-Version: 2.1
Name: tqsdk-zq-otg-rohon
Version: 1.1.2
Summary: TianQin SDK - zq_otg_rohon lib
Home-page: https://www.shinnytech.com/tqsdk
Author: TianQin
Author-email: tianqincn@gmail.com
License: UNKNOWN
Platform: UNKNOWN
Requires-Python: >=3
